exifread/__init__.py
exifread/__main__.py
exifread/cli.py
exifread/exif_log.py
exifread/py.typed
exifread/serialize.py
exifread/utils.py
exifread/core/__init__.py
exifread/core/exceptions.py
exifread/core/exif_header.py
exifread/core/find_exif.py
exifread/core/heic.py
exifread/core/ifd_tag.py
exifread/core/jpeg.py
exifread/core/jxl.py
exifread/core/utils.py
exifread/core/xmp.py
exifread/tags/__init__.py
exifread/tags/exif.py
exifread/tags/fields.py
exifread/tags/str_utils.py
exifread/tags/makernote/__init__.py
exifread/tags/makernote/apple.py
exifread/tags/makernote/canon.py
exifread/tags/makernote/casio.py
exifread/tags/makernote/dji.py
exifread/tags/makernote/fujifilm.py
exifread/tags/makernote/nikon.py
exifread/tags/makernote/olympus.py
exifread/tags/makernote/sony.py
exifread-3.5.0.dist-info/licenses/LICENSE
exifread-3.5.0.dist-info/METADATA
exifread-3.5.0.dist-info/WHEEL
exifread-3.5.0.dist-info/entry_points.txt
exifread-3.5.0.dist-info/top_level.txt
exifread-3.5.0.dist-info/RECORD
