Metadata-Version: 2.4
Name: ExifRead
Version: 3.5.0
Summary: Library to extract Exif information from digital camera image files.
Author: Ianaré Sévi
License: 
Project-URL: Repository, https://github.com/ianare/exif-py
Project-URL: Changelog, https://github.com/ianare/exif-py/blob/master/ChangeLog.rst
Keywords: exif,image,metadata,photo
Classifier: Development Status :: 5 - Production/Stable
Classifier: Environment :: Console
Classifier: Intended Audience :: Developers
Classifier: Intended Audience :: End Users/Desktop
Classifier: Operating System :: OS Independent
Classifier: Programming Language :: Python :: 3
Classifier: Programming Language :: Python :: 3 :: Only
Classifier: Topic :: Utilities
Requires-Python: >=3.7
License-File: LICENSE
Provides-Extra: dev
Requires-Dist: pre-commit~=2.21; extra == "dev"
Requires-Dist: pylint~=3.1; extra == "dev"
Requires-Dist: build~=1.0; extra == "dev"
Provides-Extra: test
Requires-Dist: pytest~=7.4; extra == "test"
Dynamic: license-file
